{"id": "3957d4df-e9ca-4c60-a06c-de28c3cfb556", "type": "add", "fields": {"associations": ["Allied States Cooperative"], "buyer_lead_agency": "ESC Region 19", "contract_files": [{"name": "17-7269sum.pdf", "url": "http://www.alliedstatescooperative.com/download_document.php?id=283&doc=contracts"}], "contract_number": "17-7269", "hub_certified": "No", "notes": "", "geographic_restrictions_allowed_states": ["ALL STATES"], "states": "TX", "suppliers": "Troxell Communications, Inc. dba Summit Integration Systems", "supplier_contacts": [{"name": "Michael Fabio/ Desiree Flanagan", "phone": "800-578-8858"}], "title": "Audio, Video, Security  and Low Voltage Equipment, Supplies and Installation- ESC Region 19- Allied States Cooperative (ASC)"}}