{"id": "4fbb1e7a-fcd5-4758-ab7c-2b321db41282", "type": "add", "fields": {"associations": ["Allied States Cooperative"], "buyer_lead_agency": "ESC Region 19", "contract_files": [{"name": "15-7098sum.pdf", "url": "http://www.alliedstatescooperative.com/download_document.php?id=198&doc=contracts"}], "contract_number": "15-7098", "hub_certified": "No", "notes": "", "geographic_restrictions_allowed_states": ["LA", " MS"], "states": "TX", "suppliers": "Automated Control Systems, Inc.", "supplier_contacts": [{"name": "Wayne Durr", "phone": "504-885-3694"}], "title": "Environmental Energy Solutions and Related Items- ESC Region 19- Allied States Cooperative (ASC)"}}