{"id":"11931d13-1502-484d-9f4f-ff61c6483de2","type":"add","fields":{"associations":["1Government Procurement Alliance"],"contract_files":[{"name":"18-16PV-07-UNI-TECH.zip","url":"https://www.1gpa.org/wp-content/uploads/2018/05/18-16PV-07-UNI-TECH.zip"}],"contract_number":"18-16PV-07","expiration":"","suppliers":"UNI-TECH","supplier_contacts":[{"name":"Jose Granado","address":"685 East Geronimo Street, Chandler, AZ 85225","phone":"480-888-026","email":"estimating@uni-tech.com / krystal@uni-tech.com"}],"title":"Job Order Contracting for Mechanical Services","amendments_files":[]}}