{"id": "056d0444-f900-48fd-a3ea-9c292a35adee", "type": "add", "fields": {"associations": ["General Services Administration"], "buyer_lead_agency": "General Services Administration", "contract_files": [{"url": "https://www.gsaadvantage.gov/ref_text/GS35F214GA/GS35F214GA_online.htm"}], "contract_number": "GS-35F-214GA", "cooperative": "True", "expiration": "Feb 07, 2022", "suppliers": "TRUSTED KNOWLEDGE OPTIONS INC.", "supplier_contacts": [{"address": "909 SWEET WILLIAM CT SE", "city": "LEESBURG", "state": "VA", "zip": "20175-5655", "phone": "(703) 508-3126", "email": "tjones@tkoptions.com"}], "title": "Order-Level Materials (OLMs) - SUBJECT TO COOPERATIVE PURCHASING", "source_url": "https://www.gsaadvantage.gov/ref_text/GS35F214GA/GS35F214GA_online.htm"}}