{"id": "0637f4e0-89f2-4fd5-8966-c7f315a500e5", "type": "add", "fields": {"associations": ["General Services Administration"], "buyer_lead_agency": "General Services Administration", "contract_files": [{"url": "https://www.gsaadvantage.gov/ref_text/GS35F0039T/GS35F0039T_online.htm"}], "contract_number": "GS-35F-0039T", "cooperative": "True", "expiration": "Oct 31, 2021", "suppliers": "TACTICAL SUPPORT EQUIPMENT, INC.", "supplier_contacts": [{"address": "4039 BAREFOOT RD", "city": "FAYETTEVILLE", "state": "NC", "zip": "28306-8254", "phone": "910-425-3360", "email": "JBRADY@TSERECON.COM"}], "title": "Purchase of New Equipment - SUBJECT TO COOPERATIVE PURCHASING", "source_url": "https://www.gsaadvantage.gov/ref_text/GS35F0039T/GS35F0039T_online.htm"}}