{"id": "06539635-70a8-4543-b2c8-b50bc7d8ae44", "type": "add", "fields": {"associations": ["General Services Administration"], "buyer_lead_agency": "General Services Administration", "contract_files": [{"url": "https://www.gsaadvantage.gov/ref_text/GS35F0046K/GS35F0046K_online.htm"}], "contract_number": "GS-35F-0046K", "cooperative": "True", "expiration": "Oct 28, 2019", "suppliers": "EIDEN SYSTEMS CORPORATION", "supplier_contacts": [{"address": "1001 RESEARCH PARK BLVD STE 410", "city": "CHARLOTTESVILLE", "state": "VA", "zip": "22911-5848", "phone": "4349747424", "email": "meiden@eidensys.com"}], "title": "Order-Level Materials (OLMs) - SUBJECT TO COOPERATIVE PURCHASING", "source_url": "https://www.gsaadvantage.gov/ref_text/GS35F0046K/GS35F0046K_online.htm"}}