{"id": "0fbdf9f2-43b0-4db9-bfcc-3fb0be868529", "type": "add", "fields": {"associations": ["General Services Administration"], "buyer_lead_agency": "General Services Administration", "contract_files": [{"url": "https://www.gsaadvantage.gov/ref_text/47QSWA18D005J/47QSWA18D005J_online.htm"}], "contract_number": "47QSWA18D005J", "cooperative": "True", "expiration": "Jun 04, 2023", "suppliers": "SAFE BOATS INTERNATIONAL LLC", "supplier_contacts": [{"address": "8800 BARNEY WHITE RD", "city": "BREMERTON", "state": "WA", "zip": "98312-4921", "phone": "360-674-7161", "email": "ldelvo@safeboats.com"}], "title": "Marine Craft", "source_url": "https://www.gsaadvantage.gov/ref_text/47QSWA18D005J/47QSWA18D005J_online.htm"}}