{"id": "13361899-314f-4a2a-a4f9-4743687b4089", "type": "add", "fields": {"associations": ["General Services Administration"], "buyer_lead_agency": "General Services Administration", "contract_files": [{"url": "https://www.gsaadvantage.gov/ref_text/GS07F265BA/GS07F265BA_online.htm"}], "contract_number": "GS-07F-265BA", "cooperative": "True", "expiration": "Jul 31, 2024", "suppliers": "MORE PREPARED, LLC", "supplier_contacts": [{"address": "4857 W 147TH ST STE C", "city": "HAWTHORNE", "state": "CA", "zip": "90250-6735", "phone": "888-733-7245", "email": "admin@moreprepared.com"}], "title": "Medical/Rescue Kits", "source_url": "https://www.gsaadvantage.gov/ref_text/GS07F265BA/GS07F265BA_online.htm"}}