{"id": "16dcf3da-5cfc-4cde-b4eb-aab1c18798c4", "type": "add", "fields": {"associations": ["General Services Administration"], "buyer_lead_agency": "General Services Administration", "contract_files": [{"url": "https://www.gsaadvantage.gov/ref_text/GS35F335GA/GS35F335GA_online.htm"}], "contract_number": "GS-35F-335GA", "cooperative": "True", "expiration": "Mar 30, 2022", "suppliers": "IDEAMATICS, INC.", "supplier_contacts": [{"address": "1364 BEVERLY RD STE 101", "city": "MC LEAN", "state": "VA", "zip": "22101-3627", "phone": "7039034972", "email": "DLDANNER@IDEAMATICS.NET"}], "title": "Term Software License - SUBJECT TO COOPERATIVE PURCHASING", "source_url": "https://www.gsaadvantage.gov/ref_text/GS35F335GA/GS35F335GA_online.htm"}}