{"id": "191d3edd-9666-4505-8e8e-76bd274de193", "type": "add", "fields": {"associations": ["General Services Administration"], "buyer_lead_agency": "General Services Administration", "contract_files": [{"url": "https://www.gsaadvantage.gov/ref_text/GS35F0649S/GS35F0649S_online.htm"}], "contract_number": "GS-35F-0649S", "cooperative": "True", "expiration": "Sep 24, 2021", "suppliers": "CAST SOFTWARE, INC.", "supplier_contacts": [{"address": "321 W 44TH ST STE 501", "city": "NEW YORK", "state": "NY", "zip": "10036-5460", "phone": "212-871-8345", "email": "B.Herrin@castsoftware.com"}], "title": "Order-Level Materials (OLMs) - SUBJECT TO COOPERATIVE PURCHASING", "source_url": "https://www.gsaadvantage.gov/ref_text/GS35F0649S/GS35F0649S_online.htm"}}