{"id": "1aa58ab8-1ffb-4239-886f-12fde414e950", "type": "add", "fields": {"associations": ["General Services Administration"], "buyer_lead_agency": "General Services Administration", "contract_files": [{"url": "https://www.gsaadvantage.gov/ref_text/GS07F0092M/GS07F0092M_online.htm"}], "contract_number": "GS-07F-0092M", "cooperative": "True", "expiration": "Nov 30, 2021", "suppliers": "DIGITAL SYSTEMS CORPORATION", "supplier_contacts": [{"address": "3 MAIN ST", "city": "WALKERSVILLE", "state": "MD", "zip": "21793-8640", "phone": "(703)898-2133", "email": "tstallone@galaxysys.com"}], "title": "Security, Alarm & Signal Systems", "source_url": "https://www.gsaadvantage.gov/ref_text/GS07F0092M/GS07F0092M_online.htm"}}