{"id": "1d58b88f-8917-4786-80bf-fdf68610cc46", "type": "add", "fields": {"associations": ["General Services Administration"], "buyer_lead_agency": "General Services Administration", "contract_files": [{"url": "https://www.gsaadvantage.gov/ref_text/GS07F225BA/GS07F225BA_online.htm"}], "contract_number": "GS-07F-225BA", "cooperative": "True", "expiration": "May 31, 2024", "suppliers": "COMMUNICATIONS PROFESSIONALS INC.", "supplier_contacts": [{"address": "2265 LIVERNOIS RD STE 900", "city": "TROY", "state": "MI", "zip": "48083-1669", "phone": "248-557-0100 EXT 103", "email": "awallace@cpgp.com"}], "title": "Footwear.  Men's Safety Toe Shoes or Boots and Women's Safety Toe Shoes or Boots", "source_url": "https://www.gsaadvantage.gov/ref_text/GS07F225BA/GS07F225BA_online.htm"}}