{"id": "218a9636-1f7a-48b2-acf2-3bfe4baf1009", "type": "add", "fields": {"associations": ["General Services Administration"], "buyer_lead_agency": "General Services Administration", "contract_files": [{"url": "https://www.gsaadvantage.gov/ref_text/GS07F0056V/GS07F0056V_online.htm"}], "contract_number": "GS-07F-0056V", "cooperative": "True", "expiration": "Oct 31, 2023", "suppliers": "BOOZ ALLEN HAMILTON INC.", "supplier_contacts": [{"address": "8283 GREENSBORO DR", "city": "MCLEAN", "state": "VA", "zip": "22102-3830", "phone": "703-902-5000", "email": "burger_noelle@bah.com"}], "title": "Order-Level Materials (OLMs) - SUBJECT TO COOPERATIVE PURCHASING", "source_url": "https://www.gsaadvantage.gov/ref_text/GS07F0056V/GS07F0056V_online.htm"}}