{"id": "248df698-36a7-4c0f-a96d-3daa4ecf5819", "type": "add", "fields": {"associations": ["General Services Administration"], "buyer_lead_agency": "General Services Administration", "contract_files": [{"url": "https://www.gsaadvantage.gov/ref_text/47QTCA19D009C/47QTCA19D009C_online.htm"}], "contract_number": "47QTCA19D009C", "cooperative": "True", "expiration": "Apr 03, 2024", "suppliers": "BAYSWATER, LLC", "supplier_contacts": [{"address": "148 BREAKWATER DR UNIT 410", "city": "SOUTH PORTLAND", "state": "ME", "zip": "04106-1656", "phone": "(646)450-7499", "email": "ymatsumura@bayswatersolutions.com"}], "title": "Information Technology Professional Services - SUBJECT TO COOPERATIVE PURCHASING", "source_url": "https://www.gsaadvantage.gov/ref_text/47QTCA19D009C/47QTCA19D009C_online.htm"}}