{"id": "28221647-b6b0-46b3-9817-b3013ab4f8c8", "type": "add", "fields": {"associations": ["General Services Administration"], "buyer_lead_agency": "General Services Administration", "contract_files": [{"url": "https://www.gsaadvantage.gov/ref_text/GS35F0439T/GS35F0439T_online.htm"}], "contract_number": "GS-35F-0439T", "cooperative": "True", "expiration": "May 20, 2022", "suppliers": "COMPUTER CONSULTANTS NORTHWEST, INC.", "supplier_contacts": [{"address": "16314 WHITETAIL LN", "city": "SUNRIVER", "state": "OR", "zip": "97707-2662", "phone": "503-375-3358", "email": "csparks@ccnw-inc.com"}], "title": "Maintenance of Equipment, Repair Services and/or Repair/Spare Parts - \r\nSUBJECT TO COOPERATIVE PURCHASING", "source_url": "https://www.gsaadvantage.gov/ref_text/GS35F0439T/GS35F0439T_online.htm"}}