{"id": "28a77077-f8f4-4eba-9452-c89206c42288", "type": "add", "fields": {"associations": ["General Services Administration"], "buyer_lead_agency": "General Services Administration", "contract_files": [{"url": "https://www.gsaadvantage.gov/ref_text/47QTCA18D00AQ/47QTCA18D00AQ_online.htm"}], "contract_number": "47QTCA18D00AQ", "cooperative": "True", "expiration": "Apr 17, 2023", "suppliers": "PRESAGIS USA INC.", "supplier_contacts": [{"address": "12424 RESEARCH PKWY STE 390", "city": "ORLANDO", "state": "FL", "zip": "32826-3271", "phone": "514-341-3874", "email": "Anthony.blankenship@presagis.com"}], "title": "Training Courses - SUBJECT TO COOPERATIVE PURCHASING", "source_url": "https://www.gsaadvantage.gov/ref_text/47QTCA18D00AQ/47QTCA18D00AQ_online.htm"}}