{"id": "29c2f1dc-24cc-4325-9563-66585cc577db", "type": "add", "fields": {"associations": ["General Services Administration"], "buyer_lead_agency": "General Services Administration", "contract_files": [{"url": "https://www.gsaadvantage.gov/ref_text/GS35F593GA/GS35F593GA_online.htm"}], "contract_number": "GS-35F-593GA", "cooperative": "True", "expiration": "Aug 14, 2022", "suppliers": "RCM SOLUTIONS, INC.", "supplier_contacts": [{"address": "4801 TESLA DRIVE SUITE C", "city": "BOWIE", "state": "MD", "zip": "20715-4327", "phone": "301-352-4901", "email": "ron.martin@rcm-corp.com"}], "title": "Information Technology Professional Services - SUBJECT TO COOPERATIVE PURCHASING", "source_url": "https://www.gsaadvantage.gov/ref_text/GS35F593GA/GS35F593GA_online.htm"}}