{"id": "3256bf5a-4954-418e-8b03-953e75585f46", "type": "add", "fields": {"associations": ["General Services Administration"], "buyer_lead_agency": "General Services Administration", "contract_files": [{"url": "https://www.gsaadvantage.gov/ref_text/GS35F279AA/GS35F279AA_online.htm"}], "contract_number": "GS-35F-279AA", "cooperative": "True", "expiration": "Mar 24, 2023", "suppliers": "REALIZATION TECHNOLOGIES, INC.", "supplier_contacts": [{"address": "440 NORTH WOLFE ROAD MS #52", "city": "SUNNYVALE", "state": "CA", "zip": "94085-3869", "phone": "(408) 271-1720", "email": "wdossani@realization.com"}], "title": "Software Maintenance Services - SUBJECT TO COOPERATIVE PURCHASING", "source_url": "https://www.gsaadvantage.gov/ref_text/GS35F279AA/GS35F279AA_online.htm"}}