{"id": "33e2ca34-eed7-4442-b6a7-7d9c895ed7f4", "type": "add", "fields": {"associations": ["General Services Administration"], "buyer_lead_agency": "General Services Administration", "contract_files": [{"url": "https://www.gsaadvantage.gov/ref_text/GS35F0586V/GS35F0586V_online.htm"}], "contract_number": "GS-35F-0586V", "cooperative": "True", "expiration": "Jul 20, 2019", "suppliers": "URS FEDERAL SERVICES, INC.", "supplier_contacts": [{"address": "20501 SENECA MEADOWS PKWY STE 30", "city": "GERMANTOWN", "state": "MD", "zip": "20876-7019", "phone": "301-944-3224", "email": "kyle.renehan@aecom.com"}], "title": "Order-Level Materials (OLMs) - SUBJECT TO COOPERATIVE PURCHASING", "source_url": "https://www.gsaadvantage.gov/ref_text/GS35F0586V/GS35F0586V_online.htm"}}