{"id": "3d37fc04-b9a5-4c54-ba28-fac139cfa599", "type": "add", "fields": {"associations": ["General Services Administration"], "buyer_lead_agency": "General Services Administration", "contract_files": [{"url": "https://www.gsaadvantage.gov/ref_text/GS35F0499X/GS35F0499X_online.htm"}], "contract_number": "GS-35F-0499X", "cooperative": "True", "expiration": "Jul 13, 2021", "suppliers": "PRODUCT DATA INTEGRATION TECHNOLOGIES, INC.", "supplier_contacts": [{"address": "4130 FABER PL DR STE 204", "city": "NORTH CHARLESTON", "state": "SC", "zip": "29405-8503", "phone": "843-743-2880", "email": "cjohnson@modulant.com"}], "title": "Order-Level Materials (OLMs) - SUBJECT TO COOPERATIVE PURCHASING", "source_url": "https://www.gsaadvantage.gov/ref_text/GS35F0499X/GS35F0499X_online.htm"}}