{"id": "3dcb8fda-c842-4732-8b94-9d6c923b836e", "type": "add", "fields": {"associations": ["General Services Administration"], "buyer_lead_agency": "General Services Administration", "contract_files": [{"url": "https://www.gsaadvantage.gov/ref_text/GS35F053DA/GS35F053DA_online.htm"}], "contract_number": "GS-35F-053DA", "cooperative": "True", "expiration": "Nov 23, 2020", "suppliers": "ISM SERVICES INCORPORATED", "supplier_contacts": [{"address": "103A WEST GEORGE ST", "city": "CARMICHAELS", "state": "PA", "zip": "15320-1209", "phone": "(724)415-9842", "email": "bill.faddis@ism-corp.us"}], "title": "Ancillary Supplies and/or Services - SUBJECT TO COOPERATIVE PURCHASING", "source_url": "https://www.gsaadvantage.gov/ref_text/GS35F053DA/GS35F053DA_online.htm"}}