{"id": "42c00723-582c-4ee8-963a-5e0f96409a43", "type": "add", "fields": {"associations": ["General Services Administration"], "buyer_lead_agency": "General Services Administration", "contract_files": [{"url": "https://www.gsaadvantage.gov/ref_text/GS35F537AA/GS35F537AA_online.htm"}], "contract_number": "GS-35F-537AA", "cooperative": "True", "expiration": "Sep 08, 2023", "suppliers": "BAUM, ROMSTEDT TECHNOLOGY RESEARCH CORPORATION", "supplier_contacts": [{"address": "8521 LEESBURG PIKE SUITE 500", "city": "VIENNA", "state": "VA", "zip": "22182-2490", "phone": "703-205-1542", "email": "peterson@brtrc.com"}], "title": "Order-Level Materials (OLMs) - SUBJECT TO COOPERATIVE PURCHASING", "source_url": "https://www.gsaadvantage.gov/ref_text/GS35F537AA/GS35F537AA_online.htm"}}