{"id": "44c47c51-5e98-4375-8ce9-e91d8083b864", "type": "add", "fields": {"associations": ["General Services Administration"], "buyer_lead_agency": "General Services Administration", "contract_files": [{"url": "https://www.gsaadvantage.gov/ref_text/GS35F286BA/GS35F286BA_online.htm"}], "contract_number": "GS-35F-286BA", "cooperative": "True", "expiration": "Mar 26, 2024", "suppliers": "SOFTEK ILLUMINATE, INC.", "supplier_contacts": [{"address": "7299 W 98TH TERR STE 130", "city": "OVERLAND PARK", "state": "KS", "zip": "66212-6183", "phone": "913-981-5293", "email": "Mary.McLenon@goilluminate.com"}], "title": "Term Software License - SUBJECT TO COOPERATIVE PURCHASING", "source_url": "https://www.gsaadvantage.gov/ref_text/GS35F286BA/GS35F286BA_online.htm"}}