{"id": "490ce138-9cc6-4849-9e0b-be37a130c2a4", "type": "add", "fields": {"associations": ["General Services Administration"], "buyer_lead_agency": "General Services Administration", "contract_files": [{"url": "https://www.gsaadvantage.gov/ref_text/GS35F025CA/GS35F025CA_online.htm"}], "contract_number": "GS-35F-025CA", "cooperative": "True", "expiration": "Oct 14, 2019", "suppliers": "OUTFITTER SATELLITE, INC.", "supplier_contacts": [{"address": "2727 OLD ELM HILL PIKE", "city": "NASHVILLE", "state": "TN", "zip": "37214-3151", "phone": "615-695-1127", "email": "m.denning@osisat.com"}], "title": "Daily/Short Term Rental - SUBJECT TO COOPERATIVE PURCHASING", "source_url": "https://www.gsaadvantage.gov/ref_text/GS35F025CA/GS35F025CA_online.htm"}}