{"id": "4b051b5b-a3ad-4891-a63d-384effb250aa", "type": "add", "fields": {"associations": ["General Services Administration"], "buyer_lead_agency": "General Services Administration", "contract_files": [{"url": "https://www.gsaadvantage.gov/ref_text/GS35F0041L/GS35F0041L_online.htm"}], "contract_number": "GS-35F-0041L", "cooperative": "True", "expiration": "Sep 30, 2020", "suppliers": "KYOCERA DOCUMENT SOLUTIONS AMERICA, INC.", "supplier_contacts": [{"address": "225 SAND RD", "city": "FAIRFIELD", "state": "NJ", "zip": "07004-1575", "phone": "973-461-4060", "email": "doris.silvius@da.kyocera.com"}], "title": "Maintenance of Equipment, Repair Services and/or Repair/Spare Parts - \r\nSUBJECT TO COOPERATIVE PURCHASING", "source_url": "https://www.gsaadvantage.gov/ref_text/GS35F0041L/GS35F0041L_online.htm"}}