{"id": "4d33c18d-1a80-438f-b919-667df8acb244", "type": "add", "fields": {"associations": ["General Services Administration"], "buyer_lead_agency": "General Services Administration", "contract_files": [{"url": "https://www.gsaadvantage.gov/ref_text/47QSWA18D00A3/47QSWA18D00A3_online.htm"}], "contract_number": "47QSWA18D00A3", "cooperative": "True", "expiration": "Sep 19, 2023", "suppliers": "COMPLETE PACKAGING & SHIPPING SUPPLIES INC.", "supplier_contacts": [{"address": "83 BENNINGTON AVE", "city": "FREEPORT", "state": "NY", "zip": "11520-3913", "phone": "800-374-3978", "email": "govsales@completepackage.com"}], "title": "Firefighting Distress/Signal Devices and Heat Sensing Devices:", "source_url": "https://www.gsaadvantage.gov/ref_text/47QSWA18D00A3/47QSWA18D00A3_online.htm"}}