{"id": "53a4339c-111b-49fb-8da5-e1de674b6775", "type": "add", "fields": {"associations": ["General Services Administration"], "buyer_lead_agency": "General Services Administration", "contract_files": [{"url": "https://www.gsaadvantage.gov/ref_text/GS35F473GA/GS35F473GA_online.htm"}], "contract_number": "GS-35F-473GA", "cooperative": "True", "expiration": "May 31, 2022", "suppliers": "TEACHPRIVACY, LLC", "supplier_contacts": [{"address": "261 OLD YORK RD STE 518", "city": "JENKINTOWN", "state": "PA", "zip": "19046-3720", "phone": "215-886-1943", "email": "felgoise@teachprivacy.com"}], "title": "Training Courses - SUBJECT TO COOPERATIVE PURCHASING", "source_url": "https://www.gsaadvantage.gov/ref_text/GS35F473GA/GS35F473GA_online.htm"}}