{"id": "54dd5431-ac3a-402d-a3d5-36c59fdf0e75", "type": "add", "fields": {"associations": ["General Services Administration"], "buyer_lead_agency": "General Services Administration", "contract_files": [{"url": "https://www.gsaadvantage.gov/ref_text/GS35F0495K/GS35F0495K_online.htm"}], "contract_number": "GS-35F-0495K", "cooperative": "True", "expiration": "Jun 27, 2020", "suppliers": "INTEGRATED COMPUTER SOLUTIONS, INC.", "supplier_contacts": [{"address": "60 COMMERCE ST STE 1100", "city": "MONTGOMERY", "state": "AL", "zip": "36104-3560", "phone": "334-356-1204", "email": "steve.goldsby@icsinc.com"}], "title": "Information Technology Professional Services - SUBJECT TO COOPERATIVE PURCHASING", "source_url": "https://www.gsaadvantage.gov/ref_text/GS35F0495K/GS35F0495K_online.htm"}}