{"id": "6150f3c0-209e-45e1-b70a-2815a3e4d0cf", "type": "add", "fields": {"associations": ["General Services Administration"], "buyer_lead_agency": "General Services Administration", "contract_files": [{"url": "https://www.gsaadvantage.gov/ref_text/47QTCA18D00GC/47QTCA18D00GC_online.htm"}], "contract_number": "47QTCA18D00GC", "cooperative": "True", "expiration": "Jul 11, 2023", "suppliers": "VINTUN LLC", "supplier_contacts": [{"address": "333 JOHN CARLYLE ST STE 540", "city": "ALEXANDRIA", "state": "VA", "zip": "22314-5767", "phone": "(717) 319-2630", "email": "matthew.nielsen@vintunllc.com"}], "title": "Order-Level Materials (OLMs) - SUBJECT TO COOPERATIVE PURCHASING", "source_url": "https://www.gsaadvantage.gov/ref_text/47QTCA18D00GC/47QTCA18D00GC_online.htm"}}