{"id": "64732646-a361-438c-83a9-6c93058aed15", "type": "add", "fields": {"associations": ["General Services Administration"], "buyer_lead_agency": "General Services Administration", "contract_files": [{"url": "https://www.gsaadvantage.gov/ref_text/GS07F0322T/GS07F0322T_online.htm"}], "contract_number": "GS-07F-0322T", "cooperative": "True", "expiration": "Apr 09, 2022", "suppliers": "SIGNET TECHNOLOGIES, INC.", "supplier_contacts": [{"address": "12300 KILN CT STE E", "city": "BELTSVILLE", "state": "MD", "zip": "20705-1357", "phone": "240-264-3295", "email": "angela.pulliam@signetinc.com"}], "title": "Physical Access Control Systems (PACS), FIPS 201 APL \u0096 SUBJECT TO COOPERATIVE PURCHASING", "source_url": "https://www.gsaadvantage.gov/ref_text/GS07F0322T/GS07F0322T_online.htm"}}