{"id": "65ba8e10-7f99-4f92-a554-0373a1f49fc4", "type": "add", "fields": {"associations": ["General Services Administration"], "buyer_lead_agency": "General Services Administration", "contract_files": [{"url": "https://www.gsaadvantage.gov/ref_text/GS35F0086U/GS35F0086U_online.htm"}], "contract_number": "GS-35F-0086U", "cooperative": "True", "expiration": "Nov 13, 2022", "suppliers": "PALANTIR TECHNOLOGIES INC.", "supplier_contacts": [{"address": "100 HAMILTON AVE STE 300", "city": "PALO ALTO", "state": "CA", "zip": "94301-1651", "phone": "650-815-0217", "email": "ckindermann@palantir.com"}], "title": "Term Software License - SUBJECT TO COOPERATIVE PURCHASING", "source_url": "https://www.gsaadvantage.gov/ref_text/GS35F0086U/GS35F0086U_online.htm"}}