{"id": "6971a99a-2919-4b62-865c-8097527ec69d", "type": "add", "fields": {"associations": ["General Services Administration"], "buyer_lead_agency": "General Services Administration", "contract_files": [{"url": "https://www.gsaadvantage.gov/ref_text/GS35F504GA/GS35F504GA_online.htm"}], "contract_number": "GS-35F-504GA", "cooperative": "True", "expiration": "Jun 14, 2022", "suppliers": "RED GATE GROUP, LIMITED, THE", "supplier_contacts": [{"address": "4795 MEADOW WOOD LANE, SUITE 135", "city": "CHANTILLY", "state": "VA", "zip": "20151-2234", "phone": "703-657-2777", "email": "wade.jost@redgategrp.com"}], "title": "Information Technology Professional Services - SUBJECT TO COOPERATIVE PURCHASING", "source_url": "https://www.gsaadvantage.gov/ref_text/GS35F504GA/GS35F504GA_online.htm"}}