{"id": "6a05da25-2325-4af0-ba5d-ded23cedde8d", "type": "add", "fields": {"associations": ["General Services Administration"], "buyer_lead_agency": "General Services Administration", "contract_files": [{"url": "https://www.gsaadvantage.gov/ref_text/GS35F0623R/GS35F0623R_online.htm"}], "contract_number": "GS-35F-0623R", "cooperative": "True", "expiration": "May 30, 2020", "suppliers": "SENTURE, LLC", "supplier_contacts": [{"address": "460 INDUSTRIAL BLVD", "city": "LONDON", "state": "KY", "zip": "40741-7285", "phone": "6068784205", "email": "chubbard@senture.com"}], "title": "Automated Contact Center Solutions (ACCS) - SUBJECT TO COOPERATIVE PURCHASING", "source_url": "https://www.gsaadvantage.gov/ref_text/GS35F0623R/GS35F0623R_online.htm"}}