{"id": "6caf01d1-18f6-406f-867b-fba1063de108", "type": "add", "fields": {"associations": ["General Services Administration"], "buyer_lead_agency": "General Services Administration", "contract_files": [{"url": "https://www.gsaadvantage.gov/ref_text/GS35F0523U/GS35F0523U_online.htm"}], "contract_number": "GS-35F-0523U", "cooperative": "True", "expiration": "Jul 30, 2023", "suppliers": "MORPHOTRAK, LLC", "supplier_contacts": [{"address": "5515 E LA PALMA AVE STE 100", "city": "ANAHEIM", "state": "CA", "zip": "92807-2116", "phone": "800-346-2674", "email": "gsasales@morphotrak.com"}], "title": "Maintenance of Equipment, Repair Services and/or Repair/Spare Parts - \r\nSUBJECT TO COOPERATIVE PURCHASING", "source_url": "https://www.gsaadvantage.gov/ref_text/GS35F0523U/GS35F0523U_online.htm"}}