{"id": "72dabc2e-72fe-4606-bc8d-8c93ae7204bd", "type": "add", "fields": {"associations": ["General Services Administration"], "buyer_lead_agency": "General Services Administration", "contract_files": [{"url": "https://www.gsaadvantage.gov/ref_text/GS35F0226W/GS35F0226W_online.htm"}], "contract_number": "GS-35F-0226W", "cooperative": "True", "expiration": "Jan 26, 2020", "suppliers": "M.C. DEAN, INC.", "supplier_contacts": [{"address": "1765 GREENSBORO STATION PLACE SU", "city": "TYSONS", "state": "VA", "zip": "22102-3467", "phone": "703-802-6231 X7143", "email": "MCDean.GSA70.IT@mcdean.com"}], "title": "Information Technology Professional Services - SUBJECT TO COOPERATIVE PURCHASING", "source_url": "https://www.gsaadvantage.gov/ref_text/GS35F0226W/GS35F0226W_online.htm"}}