{"id": "7742d8f1-7b00-460a-8ebe-29f1d1333973", "type": "add", "fields": {"associations": ["General Services Administration"], "buyer_lead_agency": "General Services Administration", "contract_files": [{"url": "https://www.gsaadvantage.gov/ref_text/GS35F0244R/GS35F0244R_online.htm"}], "contract_number": "GS-35F-0244R", "cooperative": "True", "expiration": "Jan 04, 2020", "suppliers": "AUROTECH, INC.", "supplier_contacts": [{"address": "8701 GEORGIA AVE #801", "city": "SILVER SPRING", "state": "MD", "zip": "20910-3700", "phone": "4439046080", "email": "hetal.patel@aurotechcorp.com"}], "title": "Order-Level Materials (OLMs) - SUBJECT TO COOPERATIVE PURCHASING", "source_url": "https://www.gsaadvantage.gov/ref_text/GS35F0244R/GS35F0244R_online.htm"}}