{"id": "77f5bb61-c6d6-476b-85d6-a562e68dce40", "type": "add", "fields": {"associations": ["General Services Administration"], "buyer_lead_agency": "General Services Administration", "contract_files": [{"url": "https://www.gsaadvantage.gov/ref_text/GS35F0825M/GS35F0825M_online.htm"}], "contract_number": "GS-35F-0825M", "cooperative": "True", "expiration": "Sep 25, 2022", "suppliers": "TECHNOLOGY RESOURCE CENTER OF AMERICA, LLC.", "supplier_contacts": [{"address": "2600 VIRGINIA CIRCLE", "city": "DENTON", "state": "TX", "zip": "76209-1505", "phone": "(940)891-6627", "email": "john.hunnicutt@trca.com"}], "title": "Maintenance of Equipment, Repair Services and/or Repair/Spare Parts - \r\nSUBJECT TO COOPERATIVE PURCHASING", "source_url": "https://www.gsaadvantage.gov/ref_text/GS35F0825M/GS35F0825M_online.htm"}}