{"id": "78b2744a-ef14-4665-8f56-fe72550a50a4", "type": "add", "fields": {"associations": ["General Services Administration"], "buyer_lead_agency": "General Services Administration", "contract_files": [{"url": "https://www.gsaadvantage.gov/ref_text/GS35F378BA/GS35F378BA_online.htm"}], "contract_number": "GS-35F-378BA", "cooperative": "True", "expiration": "May 29, 2019", "suppliers": "BIO-OPTRONICS, INC", "supplier_contacts": [{"address": "1890 WINTON RD S STE 190", "city": "ROCHESTER", "state": "NY", "zip": "14618-4009", "phone": "585-272-1960 X110", "email": "billing@bio-optronics.com"}], "title": "Training Courses - SUBJECT TO COOPERATIVE PURCHASING", "source_url": "https://www.gsaadvantage.gov/ref_text/GS35F378BA/GS35F378BA_online.htm"}}