{"id": "7a8db521-7cf2-48d7-b87d-e59d17900182", "type": "add", "fields": {"associations": ["General Services Administration"], "buyer_lead_agency": "General Services Administration", "contract_files": [{"url": "https://www.gsaadvantage.gov/ref_text/GS35F0501R/GS35F0501R_online.htm"}], "contract_number": "GS-35F-0501R", "cooperative": "True", "expiration": "Apr 18, 2020", "suppliers": "COMMUNICATIONS BROKERS & CONSULTANTS, INC.", "supplier_contacts": [{"address": "572 MOUNTAIN GREEN DR", "city": "CALABASAS", "state": "CA", "zip": "91302-2151", "phone": "818-591-9538", "email": "liz@callcbc.com"}], "title": "Electronic Commerce and Subscription Services \u0096 SUBJECT TO COOPERATIVE PURCHASING", "source_url": "https://www.gsaadvantage.gov/ref_text/GS35F0501R/GS35F0501R_online.htm"}}