{"id": "82feecf0-a02a-4a0e-b9da-eec030ac1e56", "type": "add", "fields": {"associations": ["General Services Administration"], "buyer_lead_agency": "General Services Administration", "contract_files": [{"url": "https://www.gsaadvantage.gov/ref_text/GS35F0308L/GS35F0308L_online.htm"}], "contract_number": "GS-35F-0308L", "cooperative": "True", "expiration": "Mar 25, 2021", "suppliers": "QUALITY SOFTWARE SERVICES, INC.", "supplier_contacts": [{"address": "10480 LITTLE PATUXENT PKWY SUITE", "city": "COLUMBIA", "state": "MD", "zip": "21044-3575", "phone": "301-977-7884", "email": "ddnoche@qssinc.com"}], "title": "Homeland Security Presidential Directive 12 Product and Service Components - SUBJECT TO COOPERATIVE PURCHASING", "source_url": "https://www.gsaadvantage.gov/ref_text/GS35F0308L/GS35F0308L_online.htm"}}