{"id": "8395018e-f125-49d3-b9d0-04129e518d24", "type": "add", "fields": {"associations": ["General Services Administration"], "buyer_lead_agency": "General Services Administration", "contract_files": [{"url": "https://www.gsaadvantage.gov/ref_text/GS35F0077R/GS35F0077R_online.htm"}], "contract_number": "GS-35F-0077R", "cooperative": "True", "expiration": "Oct 31, 2019", "suppliers": "PERFORMAX 3, INC", "supplier_contacts": [{"address": "2555 ENTERPRISE RD STE 8", "city": "CLEARWATER", "state": "FL", "zip": "33763-1104", "phone": "1.888.752.6299", "email": "dan.wright@performax3.com"}], "title": "Software Maintenance Services - SUBJECT TO COOPERATIVE PURCHASING", "source_url": "https://www.gsaadvantage.gov/ref_text/GS35F0077R/GS35F0077R_online.htm"}}