{"id": "85e53c84-11f0-41d3-8641-4521390c8a9c", "type": "add", "fields": {"associations": ["General Services Administration"], "buyer_lead_agency": "General Services Administration", "contract_files": [{"url": "https://www.gsaadvantage.gov/ref_text/GS35F113GA/GS35F113GA_online.htm"}], "contract_number": "GS-35F-113GA", "cooperative": "True", "expiration": "Dec 08, 2021", "suppliers": "IRIS INTELLIGENCE LIMITED", "supplier_contacts": [{"address": "24 BARTON STREET", "city": "BATH", "state": "  ", "zip": "BA1 1HG", "phone": "6465153752", "email": "tmobley@irisintelligence.com"}], "title": "Cloud and Cloud-Related IT Professional Services  - SUBJECT TO COOPERATIVE PURCHASING", "source_url": "https://www.gsaadvantage.gov/ref_text/GS35F113GA/GS35F113GA_online.htm"}}