{"id": "88eabbd5-8128-42fd-a59e-fcb9863b9430", "type": "add", "fields": {"associations": ["General Services Administration"], "buyer_lead_agency": "General Services Administration", "contract_files": [{"url": "https://www.gsaadvantage.gov/ref_text/GS35F177DA/GS35F177DA_online.htm"}], "contract_number": "GS-35F-177DA", "cooperative": "True", "expiration": "Feb 11, 2021", "suppliers": "COOPER CONSULTING COMPANY", "supplier_contacts": [{"address": "601 FARLEY DR", "city": "AUSTIN", "state": "TX", "zip": "78753-3114", "phone": "(512) 527-1000", "email": "caudle@cooperconsulting.com"}], "title": "Information Technology Professional Services - SUBJECT TO COOPERATIVE PURCHASING", "source_url": "https://www.gsaadvantage.gov/ref_text/GS35F177DA/GS35F177DA_online.htm"}}