{"id": "89032e08-f385-42e1-880b-b3a01959cba4", "type": "add", "fields": {"associations": ["General Services Administration"], "buyer_lead_agency": "General Services Administration", "contract_files": [{"url": "https://www.gsaadvantage.gov/ref_text/GS35F248DA/GS35F248DA_online.htm"}], "contract_number": "GS-35F-248DA", "cooperative": "True", "expiration": "Mar 29, 2021", "suppliers": "GENEVA SOFTWARE, INC.", "supplier_contacts": [{"address": "2121 COOPERATIVE WAY STE 300", "city": "HERNDON", "state": "VA", "zip": "20171-5186", "phone": "703-471-7666", "email": "CZika@genevasi.com"}], "title": "Information Technology Professional Services - SUBJECT TO COOPERATIVE PURCHASING", "source_url": "https://www.gsaadvantage.gov/ref_text/GS35F248DA/GS35F248DA_online.htm"}}