{"id": "8a3bee99-fa10-40ba-bbee-0d6ac10e07a5", "type": "add", "fields": {"associations": ["General Services Administration"], "buyer_lead_agency": "General Services Administration", "contract_files": [{"url": "https://www.gsaadvantage.gov/ref_text/GS35F0354T/GS35F0354T_online.htm"}], "contract_number": "GS-35F-0354T", "cooperative": "True", "expiration": "Mar 28, 2022", "suppliers": "AXISCORE, LLC", "supplier_contacts": [{"address": "1629 K ST. SUITE 300", "city": "WASHINGTON", "state": "DC", "zip": "20006-1631", "phone": "2022806577", "email": "ekeneu@axiscoreonline.com"}], "title": "Order-Level Materials (OLMs) - SUBJECT TO COOPERATIVE PURCHASING", "source_url": "https://www.gsaadvantage.gov/ref_text/GS35F0354T/GS35F0354T_online.htm"}}