{"id": "9962834c-2022-4b79-9c3d-6d77b294e4a0", "type": "add", "fields": {"associations": ["General Services Administration"], "buyer_lead_agency": "General Services Administration", "contract_files": [{"url": "https://www.gsaadvantage.gov/ref_text/GS35F0242R/GS35F0242R_online.htm"}], "contract_number": "GS-35F-0242R", "cooperative": "True", "expiration": "Jan 03, 2020", "suppliers": "IDEMIA IDENTITY & SECURITY USA LLC", "supplier_contacts": [{"address": "296 CONCORD RD STE 300", "city": "BILLERICA", "state": "MA", "zip": "01821-3487", "phone": "(952)979-8477", "email": "tmcpherson@morphotrust.com"}], "title": "Software Maintenance Services - SUBJECT TO COOPERATIVE PURCHASING", "source_url": "https://www.gsaadvantage.gov/ref_text/GS35F0242R/GS35F0242R_online.htm"}}