{"id": "9a8a5a83-a023-459c-afc1-e1d6b6382cfc", "type": "add", "fields": {"associations": ["General Services Administration"], "buyer_lead_agency": "General Services Administration", "contract_files": [{"url": "https://www.gsaadvantage.gov/ref_text/GS35F326CA/GS35F326CA_online.htm"}], "contract_number": "GS-35F-326CA", "cooperative": "True", "expiration": "May 13, 2020", "suppliers": "ATLANTIC SYSTEMS GROUP, INC.", "supplier_contacts": [{"address": "5737 INDIGO CROSSING DR", "city": "ROCKLEDGE", "state": "FL", "zip": "32955-6014", "phone": "301-358-2690", "email": "rschmelz@asg.cc"}], "title": "Order-Level Materials (OLMs) - SUBJECT TO COOPERATIVE PURCHASING", "source_url": "https://www.gsaadvantage.gov/ref_text/GS35F326CA/GS35F326CA_online.htm"}}