{"id": "9b5f72ab-3e8f-47ce-9772-76b18f76f2b9", "type": "add", "fields": {"associations": ["General Services Administration"], "buyer_lead_agency": "General Services Administration", "contract_files": [{"url": "https://www.gsaadvantage.gov/ref_text/GS35F0056S/GS35F0056S_online.htm"}], "contract_number": "GS-35F-0056S", "cooperative": "True", "expiration": "Nov 06, 2020", "suppliers": "SIGNAL MOUNTAIN NETWORKS, INC.", "supplier_contacts": [{"address": "2320 CHAMBLEE TUCKER RD", "city": "ATLANTA", "state": "GA", "zip": "30341-3447", "phone": "6782627009", "email": "luis.valenzuela@signalmountain.com"}], "title": "Maintenance of Equipment, Repair Services and/or Repair/Spare Parts - \r\nSUBJECT TO COOPERATIVE PURCHASING", "source_url": "https://www.gsaadvantage.gov/ref_text/GS35F0056S/GS35F0056S_online.htm"}}