{"id": "9d563b09-3e2f-4cf1-9a18-fa53f31315e5", "type": "add", "fields": {"associations": ["General Services Administration"], "buyer_lead_agency": "General Services Administration", "contract_files": [{"url": "https://www.gsaadvantage.gov/ref_text/GS35F206DA/GS35F206DA_online.htm"}], "contract_number": "GS-35F-206DA", "cooperative": "True", "expiration": "Feb 28, 2021", "suppliers": "CARTRIDGE SAVERS, INC.", "supplier_contacts": [{"address": "2801 COHO ST STE 206", "city": "MADISON", "state": "WI", "zip": "53713-4531", "phone": "608 227-7283", "email": "SALES@CARTRIDGESAVERS.COM"}], "title": "Maintenance of Equipment, Repair Services and/or Repair/Spare Parts - \r\nSUBJECT TO COOPERATIVE PURCHASING", "source_url": "https://www.gsaadvantage.gov/ref_text/GS35F206DA/GS35F206DA_online.htm"}}