{"id": "a8329cb2-0075-4404-bb02-6e43805865a4", "type": "add", "fields": {"associations": ["General Services Administration"], "buyer_lead_agency": "General Services Administration", "contract_files": [{"url": "https://www.gsaadvantage.gov/ref_text/GS35F217AA/GS35F217AA_online.htm"}], "contract_number": "GS-35F-217AA", "cooperative": "True", "expiration": "Feb 24, 2023", "suppliers": "UNCOMN, LLC", "supplier_contacts": [{"address": "735 SEIBERT RD STE 4", "city": "SCOTT AFB", "state": "IL", "zip": "62225-1538", "phone": "618-215-5615", "email": "ldunniing@uncomn.com"}], "title": "Information Technology Professional Services - SUBJECT TO COOPERATIVE PURCHASING", "source_url": "https://www.gsaadvantage.gov/ref_text/GS35F217AA/GS35F217AA_online.htm"}}