{"id": "ac4c7c2e-9d50-4cc8-a73d-ad97f85ec2dc", "type": "add", "fields": {"associations": ["General Services Administration"], "buyer_lead_agency": "General Services Administration", "contract_files": [{"url": "https://www.gsaadvantage.gov/ref_text/GS35F0503X/GS35F0503X_online.htm"}], "contract_number": "GS-35F-0503X", "cooperative": "True", "expiration": "Jul 14, 2021", "suppliers": "BETTER DIRECT, LLC", "supplier_contacts": [{"address": "2425 E UNIVERSITY DR", "city": "TEMPE", "state": "AZ", "zip": "85281-3110", "phone": "866-921-3858 EX: 202", "email": "mark@betterdirect.com"}], "title": "Purchase of Used or Refurbished Equipment - SUBJECT TO COOPERATIVE PURCHASING", "source_url": "https://www.gsaadvantage.gov/ref_text/GS35F0503X/GS35F0503X_online.htm"}}