{"id": "b0895788-c659-4111-a637-e3c1ad5d89e7", "type": "add", "fields": {"associations": ["General Services Administration"], "buyer_lead_agency": "General Services Administration", "contract_files": [{"url": "https://www.gsaadvantage.gov/ref_text/GS35F0490U/GS35F0490U_online.htm"}], "contract_number": "GS-35F-0490U", "cooperative": "True", "expiration": "Jul 10, 2023", "suppliers": "ICOHERE, INC.", "supplier_contacts": [{"address": "1220 OAKLAND BLVD STE 210", "city": "WALNUT CREEK", "state": "CA", "zip": "94596-4388", "phone": "202-870-6146", "email": "lance@icohere.com"}], "title": "Order-Level Materials (OLMs) - SUBJECT TO COOPERATIVE PURCHASING", "source_url": "https://www.gsaadvantage.gov/ref_text/GS35F0490U/GS35F0490U_online.htm"}}