{"id": "b90a7878-6808-42a8-8a29-2de1030a408c", "type": "add", "fields": {"associations": ["General Services Administration"], "buyer_lead_agency": "General Services Administration", "contract_files": [{"url": "https://www.gsaadvantage.gov/ref_text/GS07F0307X/GS07F0307X_online.htm"}], "contract_number": "GS-07F-0307X", "cooperative": "True", "expiration": "Feb 28, 2021", "suppliers": "NABCO SYSTEMS, LLC", "supplier_contacts": [{"address": "171 HILLPOINTE DR #303", "city": "CANONSBURG", "state": "PA", "zip": "15317-9554", "phone": "724-746-9617", "email": "bpresutti@nabcosystems.com"}], "title": "Bomb Disposal and Hazardous Material Protective and Detective Equipment", "source_url": "https://www.gsaadvantage.gov/ref_text/GS07F0307X/GS07F0307X_online.htm"}}