{"id": "bbffa539-ff0a-4a14-9bcb-73fcf7f28fd7", "type": "add", "fields": {"associations": ["General Services Administration"], "buyer_lead_agency": "General Services Administration", "contract_files": [{"url": "https://www.gsaadvantage.gov/ref_text/GS35F363AA/GS35F363AA_online.htm"}], "contract_number": "GS-35F-363AA", "cooperative": "True", "expiration": "May 01, 2023", "suppliers": "INFORMATION UNLIMITED INC.", "supplier_contacts": [{"address": "500 PENN ST NE", "city": "WASHINGTON", "state": "DC", "zip": "20002-7024", "phone": "202-600-4431", "email": "herschel.chandler@iui.com"}], "title": "Information Technology Professional Services - SUBJECT TO COOPERATIVE PURCHASING", "source_url": "https://www.gsaadvantage.gov/ref_text/GS35F363AA/GS35F363AA_online.htm"}}