{"id": "bc04477f-7605-4324-a939-e81405c65f79", "type": "add", "fields": {"associations": ["General Services Administration"], "buyer_lead_agency": "General Services Administration", "contract_files": [{"url": "https://www.gsaadvantage.gov/ref_text/GS07F161DA/GS07F161DA_online.htm"}], "contract_number": "GS-07F-161DA", "cooperative": "True", "expiration": "Aug 07, 2021", "suppliers": "VISION TECHNOLOGIES, INC.", "supplier_contacts": [{"address": "530 MCCORMICK DR STE G", "city": "GLEN BURNIE", "state": "MD", "zip": "21061-8200", "phone": "410-691-3109", "email": "asaxon@visiontech.biz"}], "title": "Law Enforcement", "source_url": "https://www.gsaadvantage.gov/ref_text/GS07F161DA/GS07F161DA_online.htm"}}