{"id": "bd400b38-48f1-49a4-a39b-b501d9c34e72", "type": "add", "fields": {"associations": ["General Services Administration"], "buyer_lead_agency": "General Services Administration", "contract_files": [{"url": "https://www.gsaadvantage.gov/ref_text/GS35F0329X/GS35F0329X_online.htm"}], "contract_number": "GS-35F-0329X", "cooperative": "True", "expiration": "Apr 07, 2021", "suppliers": "ENTERPRISE TECHNOLOGY SOLUTIONS, INC.", "supplier_contacts": [{"address": "9502 BROOKE DRIVE", "city": "BETHESDA", "state": "MD", "zip": "20817-2207", "phone": "925 353 5009", "email": "smith@enterprisesol.com"}], "title": "Purchase of New Equipment - SUBJECT TO COOPERATIVE PURCHASING", "source_url": "https://www.gsaadvantage.gov/ref_text/GS35F0329X/GS35F0329X_online.htm"}}