{"id": "bfdd46b0-66bd-4262-95ed-9b6ef594aca0", "type": "add", "fields": {"associations": ["General Services Administration"], "buyer_lead_agency": "General Services Administration", "contract_files": [{"url": "https://www.gsaadvantage.gov/ref_text/GS35F0673M/GS35F0673M_online.htm"}], "contract_number": "GS-35F-0673M", "cooperative": "True", "expiration": "Aug 04, 2022", "suppliers": "STELLAR SERVICES, INC.", "supplier_contacts": [{"address": "70 W 36TH ST FL 7", "city": "NEW YORK", "state": "NY", "zip": "10018-1258", "phone": "2124322848", "email": "contact@StellarServices.com"}], "title": "Information Technology Professional Services - SUBJECT TO COOPERATIVE PURCHASING", "source_url": "https://www.gsaadvantage.gov/ref_text/GS35F0673M/GS35F0673M_online.htm"}}