{"id": "c0ea5f73-4151-43a1-93a2-046cb13fb9e1", "type": "add", "fields": {"associations": ["General Services Administration"], "buyer_lead_agency": "General Services Administration", "contract_files": [{"url": "https://www.gsaadvantage.gov/ref_text/GS35F0203U/GS35F0203U_online.htm"}], "contract_number": "GS-35F-0203U", "cooperative": "True", "expiration": "Jan 17, 2023", "suppliers": "C4 PLANNING SOLUTIONS, LLC", "supplier_contacts": [{"address": "4914 DEANS BRIDGE RD", "city": "BLYTHE", "state": "GA", "zip": "30805-3518", "phone": "7065923095", "email": "joe.colpaert@c4plans.com"}], "title": "Order-Level Materials (OLMs) - SUBJECT TO COOPERATIVE PURCHASING", "source_url": "https://www.gsaadvantage.gov/ref_text/GS35F0203U/GS35F0203U_online.htm"}}