{"id": "c2f9978b-1ee2-4fd8-ab44-4d3c3de1a150", "type": "add", "fields": {"associations": ["General Services Administration"], "buyer_lead_agency": "General Services Administration", "contract_files": [{"url": "https://www.gsaadvantage.gov/ref_text/GS35F0360L/GS35F0360L_online.htm"}], "contract_number": "GS-35F-0360L", "cooperative": "True", "expiration": "Apr 22, 2021", "suppliers": "ALIGNED DEVELOPMENT STRATEGIES, INCORPORATED", "supplier_contacts": [{"address": "1900 L ST NW STE 600", "city": "WASHINGTON", "state": "DC", "zip": "20036-5051", "phone": "202-659-2807", "email": "dgjames@goADSI.com"}], "title": "Purchase of New Equipment - SUBJECT TO COOPERATIVE PURCHASING", "source_url": "https://www.gsaadvantage.gov/ref_text/GS35F0360L/GS35F0360L_online.htm"}}