{"id": "c5d14e54-2580-482a-8439-22ccc8da166c", "type": "add", "fields": {"associations": ["General Services Administration"], "buyer_lead_agency": "General Services Administration", "contract_files": [{"url": "https://www.gsaadvantage.gov/ref_text/GS35F0909P/GS35F0909P_online.htm"}], "contract_number": "GS-35F-0909P", "cooperative": "True", "expiration": "Sep 29, 2019", "suppliers": "ALLIANCE CONSULTING CORP.", "supplier_contacts": [{"address": "7529 STANDISH PL STE 104", "city": "ROCKVILLE", "state": "MD", "zip": "20855-2733", "phone": "301-294-9290", "email": "sbedi@alliancecorp.net"}], "title": "Information Technology Professional Services - SUBJECT TO COOPERATIVE PURCHASING", "source_url": "https://www.gsaadvantage.gov/ref_text/GS35F0909P/GS35F0909P_online.htm"}}