{"id": "cd80045d-9920-4957-9298-37f367872445", "type": "add", "fields": {"associations": ["General Services Administration"], "buyer_lead_agency": "General Services Administration", "contract_files": [{"url": "https://www.gsaadvantage.gov/ref_text/GS35F0047L/GS35F0047L_online.htm"}], "contract_number": "GS-35F-0047L", "cooperative": "True", "expiration": "Oct 25, 2020", "suppliers": "LCG SYSTEMS LLC", "supplier_contacts": [{"address": "6000 EXECUTIVE BLVD STE 410", "city": "ROCKVILLE", "state": "MD", "zip": "20852-3803", "phone": "703-248-2077", "email": "kristin.nichols@lcginc.com"}], "title": "Order-Level Materials (OLMs) - SUBJECT TO COOPERATIVE PURCHASING", "source_url": "https://www.gsaadvantage.gov/ref_text/GS35F0047L/GS35F0047L_online.htm"}}