{"id": "d029a1fc-5335-442a-823e-8eed61352456", "type": "add", "fields": {"associations": ["General Services Administration"], "buyer_lead_agency": "General Services Administration", "contract_files": [{"url": "https://www.gsaadvantage.gov/ref_text/GS07F0120V/GS07F0120V_online.htm"}], "contract_number": "GS-07F-0120V", "cooperative": "True", "expiration": "Jan 31, 2024", "suppliers": "VICTOR FORWARD LLC", "supplier_contacts": [{"address": "549 PROGRESS LANE SUITE 101", "city": "VIRGINIA BEACH", "state": "VA", "zip": "23454-3476", "phone": "800-958-1601", "email": "sales@victorforward.com"}], "title": "Shipboard/Aircraft Anti-Exposure Immersion Clothing Not Otherwise Covered", "source_url": "https://www.gsaadvantage.gov/ref_text/GS07F0120V/GS07F0120V_online.htm"}}