{"id": "d15a6afa-f8cf-4569-b06e-d568be590df5", "type": "add", "fields": {"associations": ["General Services Administration"], "buyer_lead_agency": "General Services Administration", "contract_files": [{"url": "https://www.gsaadvantage.gov/ref_text/GS35F598GA/GS35F598GA_online.htm"}], "contract_number": "GS-35F-598GA", "cooperative": "True", "expiration": "Aug 04, 2022", "suppliers": "PLANNED SYSTEMS INTERNATIONAL, INC.", "supplier_contacts": [{"address": "10632 LITTLE PATUXENT PKWY STE 2", "city": "COLUMBIA", "state": "MD", "zip": "21044-6250", "phone": "443-832-5018", "email": "dabed@plan-sys.com"}], "title": "Health Information Technology Services - SUBJECT TO COOPERATIVE PURCHASING", "source_url": "https://www.gsaadvantage.gov/ref_text/GS35F598GA/GS35F598GA_online.htm"}}