{"id": "d25ebba9-17e1-4253-a9cd-f8dc198513b8", "type": "add", "fields": {"associations": ["General Services Administration"], "buyer_lead_agency": "General Services Administration", "contract_files": [{"url": "https://www.gsaadvantage.gov/ref_text/GS07F5769R/GS07F5769R_online.htm"}], "contract_number": "GS-07F-5769R", "cooperative": "True", "expiration": "Apr 14, 2020", "suppliers": "BLASTGARD INTERNATIONAL, INC.", "supplier_contacts": [{"address": "2451 MCMULLEN BOOTH RD STE 212", "city": "CLEARWATER", "state": "FL", "zip": "33759-1362", "phone": "(727)592-9400", "email": "mgordon@blastgardintl.com"}], "title": "Bomb Disposal and Hazardous Material Protective and Detective Equipment", "source_url": "https://www.gsaadvantage.gov/ref_text/GS07F5769R/GS07F5769R_online.htm"}}