{"id": "d5f6e850-bc34-4f65-8d04-7b39b8aef318", "type": "add", "fields": {"associations": ["General Services Administration"], "buyer_lead_agency": "General Services Administration", "contract_files": [{"url": "https://www.gsaadvantage.gov/ref_text/47QTCA18D004Y/47QTCA18D004Y_online.htm"}], "contract_number": "47QTCA18D004Y", "cooperative": "True", "expiration": "Jan 02, 2023", "suppliers": "METROPOLE PRODUCTS, INC.", "supplier_contacts": [{"address": "2040 JEFFERSON DAVIS HWY", "city": "STAFFORD", "state": "VA", "zip": "22554-7219", "phone": "540-659-2132", "email": "bbuder@metropoleproducts.com"}], "title": "Purchase of New Equipment - SUBJECT TO COOPERATIVE PURCHASING", "source_url": "https://www.gsaadvantage.gov/ref_text/47QTCA18D004Y/47QTCA18D004Y_online.htm"}}