{"id": "dd50bbc6-89ab-4bab-83d3-ecccaa8a25b1", "type": "add", "fields": {"associations": ["General Services Administration"], "buyer_lead_agency": "General Services Administration", "contract_files": [{"url": "https://www.gsaadvantage.gov/ref_text/GS35F291AA/GS35F291AA_online.htm"}], "contract_number": "GS-35F-291AA", "cooperative": "True", "expiration": "Mar 26, 2023", "suppliers": "3DI, INC.", "supplier_contacts": [{"address": "3 POINTE DR STE# 307", "city": "BREA", "state": "CA", "zip": "92821-6271", "phone": "7032838201", "email": "regina.ellis@gsa.gov"}], "title": "Order-Level Materials (OLMs) - SUBJECT TO COOPERATIVE PURCHASING", "source_url": "https://www.gsaadvantage.gov/ref_text/GS35F291AA/GS35F291AA_online.htm"}}