{"id": "dfc8e1cc-6e3c-48d3-ba96-f56a50c12be5", "type": "add", "fields": {"associations": ["General Services Administration"], "buyer_lead_agency": "General Services Administration", "contract_files": [{"url": "https://www.gsaadvantage.gov/ref_text/47QTCA18D00HC/47QTCA18D00HC_online.htm"}], "contract_number": "47QTCA18D00HC", "cooperative": "True", "expiration": "Aug 01, 2023", "suppliers": "DOTNET SECURITY SOLUTIONS, LLC", "supplier_contacts": [{"address": "1152 REGAL HILLS LN", "city": "MABLETON", "state": "GA", "zip": "30126-7275", "phone": "6782310045", "email": "jyancie@dotnetss.com"}], "title": "Highly Adaptive Cybersecurity Services (HACS)-SUBJECT TO COOPERATIVE PURCHASING", "source_url": "https://www.gsaadvantage.gov/ref_text/47QTCA18D00HC/47QTCA18D00HC_online.htm"}}