{"id": "ec239d15-fc2e-492a-b722-6302540d9e70", "type": "add", "fields": {"associations": ["General Services Administration"], "buyer_lead_agency": "General Services Administration", "contract_files": [{"url": "https://www.gsaadvantage.gov/ref_text/GS35F0514M/GS35F0514M_online.htm"}], "contract_number": "GS-35F-0514M", "cooperative": "True", "expiration": "May 30, 2022", "suppliers": "GAP SOLUTIONS, INC.", "supplier_contacts": [{"address": "205 VAN BUREN ST STE 205", "city": "HERNDON", "state": "VA", "zip": "20170-5348", "phone": "7039641569", "email": "ECONTRERAS@GAPSI.COM"}], "title": "Order-Level Materials (OLMs) - SUBJECT TO COOPERATIVE PURCHASING", "source_url": "https://www.gsaadvantage.gov/ref_text/GS35F0514M/GS35F0514M_online.htm"}}