{"id": "f1b32973-ef67-4ab9-a7cb-ca1ddb9dee33", "type": "add", "fields": {"associations": ["General Services Administration"], "buyer_lead_agency": "General Services Administration", "contract_files": [{"url": "https://www.gsaadvantage.gov/ref_text/GS35F501GA/GS35F501GA_online.htm"}], "contract_number": "GS-35F-501GA", "cooperative": "True", "expiration": "Jun 11, 2022", "suppliers": "GLOBAL KNOWLEDGE TRAINING LLC", "supplier_contacts": [{"address": "9000 REGENCY PKWY STE 400", "city": "CARY", "state": "NC", "zip": "27518-8520", "phone": "919-469-7019", "email": "lara.geiger@globalknowledge.com"}], "title": "Training Courses - SUBJECT TO COOPERATIVE PURCHASING", "source_url": "https://www.gsaadvantage.gov/ref_text/GS35F501GA/GS35F501GA_online.htm"}}