{"id": "f1fb53d7-28aa-4df1-b268-043712919d3f", "type": "add", "fields": {"associations": ["General Services Administration"], "buyer_lead_agency": "General Services Administration", "contract_files": [{"url": "https://www.gsaadvantage.gov/ref_text/GS35F0449P/GS35F0449P_online.htm"}], "contract_number": "GS-35F-0449P", "cooperative": "True", "expiration": "Apr 15, 2024", "suppliers": "METAFORMERS, INC.", "supplier_contacts": [{"address": "1850 CENTENNIAL PARK DR, SUITE 1", "city": "RESTON", "state": "VA", "zip": "20191-1517", "phone": "7032884620", "email": "paul.stewart@metaformers.com"}], "title": "Order-Level Materials (OLMs) - SUBJECT TO COOPERATIVE PURCHASING", "source_url": "https://www.gsaadvantage.gov/ref_text/GS35F0449P/GS35F0449P_online.htm"}}