{"id": "fad8bf11-4af3-4d37-b0c6-7cf8d62e852b", "type": "add", "fields": {"associations": ["General Services Administration"], "buyer_lead_agency": "General Services Administration", "contract_files": [{"url": "https://www.gsaadvantage.gov/ref_text/GS35F0319T/GS35F0319T_online.htm"}], "contract_number": "GS-35F-0319T", "cooperative": "True", "expiration": "Mar 08, 2022", "suppliers": "KBTS TECHNOLOGIES, INC", "supplier_contacts": [{"address": "41461 W 11 MILE RD", "city": "NOVI", "state": "MI", "zip": "48375-1855", "phone": "2483741230", "email": "andy@kbtstech.com"}], "title": "Order-Level Materials (OLMs) - SUBJECT TO COOPERATIVE PURCHASING", "source_url": "https://www.gsaadvantage.gov/ref_text/GS35F0319T/GS35F0319T_online.htm"}}