{"id": "fbcd40dd-6e32-4812-91e5-3bb903ffa6e3", "type": "add", "fields": {"associations": ["General Services Administration"], "buyer_lead_agency": "General Services Administration", "contract_files": [{"url": "https://www.gsaadvantage.gov/ref_text/GS35F0782J/GS35F0782J_online.htm"}], "contract_number": "GS-35F-0782J", "cooperative": "True", "expiration": "Sep 23, 2019", "suppliers": "COMBYTE U S A", "supplier_contacts": [{"address": "5415 EASTON DR", "city": "SPRINGFIELD", "state": "VA", "zip": "22151-3415", "phone": "703-642-5100", "email": "ben@combyteusa.com"}], "title": "Term Software License - SUBJECT TO COOPERATIVE PURCHASING", "source_url": "https://www.gsaadvantage.gov/ref_text/GS35F0782J/GS35F0782J_online.htm"}}