{"id": "fdc23f27-c251-4862-852f-ab9653497bbf", "type": "add", "fields": {"associations": ["General Services Administration"], "buyer_lead_agency": "General Services Administration", "contract_files": [{"url": "https://www.gsaadvantage.gov/ref_text/GS35F0142V/GS35F0142V_online.htm"}], "contract_number": "GS-35F-0142V", "cooperative": "True", "expiration": "Dec 18, 2023", "suppliers": "BLACKWOOD ASSOCIATES, INC.", "supplier_contacts": [{"address": "1835 FOREST DR STE A", "city": "ANNAPOLIS", "state": "MD", "zip": "21401-4432", "phone": "4435695496", "email": "WHITNEY@BAIFEDERAL.COM"}], "title": "Purchase of New Equipment - SUBJECT TO COOPERATIVE PURCHASING", "source_url": "https://www.gsaadvantage.gov/ref_text/GS35F0142V/GS35F0142V_online.htm"}}