{"id": "fe58ddb2-9a64-43b3-8a59-b4310380cef9", "type": "add", "fields": {"associations": ["General Services Administration"], "buyer_lead_agency": "General Services Administration", "contract_files": [{"url": "https://www.gsaadvantage.gov/ref_text/GS35F0660V/GS35F0660V_online.htm"}], "contract_number": "GS-35F-0660V", "cooperative": "True", "expiration": "Aug 26, 2019", "suppliers": "DIRECTIONS TRAINING CENTER, INC.", "supplier_contacts": [{"address": "2625 BUTTERFIELD RD STE 312E", "city": "OAK BROOK", "state": "IL", "zip": "60523-1281", "phone": "630-326-5176", "email": "bmcsweeney@directionstraining.com"}], "title": "Training Courses - SUBJECT TO COOPERATIVE PURCHASING", "source_url": "https://www.gsaadvantage.gov/ref_text/GS35F0660V/GS35F0660V_online.htm"}}